daqbrokerClient.py
parsingFuncs.py
sync.py
DAQBrokerClient-0.0.2.dist-info/METADATA
DAQBrokerClient-0.0.2.dist-info/RECORD
DAQBrokerClient-0.0.2.dist-info/WHEEL
DAQBrokerClient-0.0.2.dist-info/top_level.txt
