Metadata-Version: 2.1
Name: DAQBrokerClient
Version: 0.0.2
Summary: Client for the DAQBroker server application
Home-page: https://daqbroker.com
Author: daqbroker
Author-email: support@daqbroker.com
License: UNKNOWN
Project-URL: Bug Reports, https://github.com/daqbroker/daqbroker/issues
Project-URL: Source, https://github.com/daqbroker/daqbroker
Keywords: monitoring scientific instrument data
Platform: UNKNOWN
Classifier: Development Status :: 4 - Beta
Classifier: Intended Audience :: Developers
Classifier: Intended Audience :: Science/Research
Classifier: Intended Audience :: Information Technology
Classifier: License :: OSI Approved :: MIT License
Classifier: Programming Language :: Python :: 3
Classifier: Programming Language :: Python :: 3.4
Classifier: Programming Language :: Python :: 3.5
Classifier: Programming Language :: Python :: 3.6
Classifier: Operating System :: POSIX :: Linux
Classifier: Operating System :: Microsoft :: Windows  
Requires-Dist: ntplib
Requires-Dist: psutil
Requires-Dist: pyAesCrypt
Requires-Dist: snowflake
Requires-Dist: concurrent-log-handler
Requires-Dist: numpy
Requires-Dist: pyzmq
Requires-Dist: concurrent-log-handler
Requires-Dist: requests
Requires-Dist: arrow
